urban_worm-0.1.2.dist-info/licenses/LICENSE
urbanworm/__init__.py
urbanworm/dataset.py
urbanworm/inference/Inference.py
urbanworm/inference/__init__.py
urbanworm/inference/format.py
urbanworm/inference/llama.py
urbanworm/inference/transformers.py
urbanworm/models/__init__.py
urbanworm/models/face_detection_yunet_2023mar.onnx
urbanworm/utils/__init__.py
urbanworm/utils/building.py
urbanworm/utils/pano2pers.py
urbanworm/utils/utils.py
urban_worm-0.1.2.dist-info/METADATA
urban_worm-0.1.2.dist-info/WHEEL
urban_worm-0.1.2.dist-info/top_level.txt
urban_worm-0.1.2.dist-info/RECORD
