Metadata-Version: 2.4
Name: urban-worm
Version: 0.1.2
Summary: Workflow of reproducible multimodal inference for urban environment evaluation.
Author-email: Xiaohao Yang <xiaohaoy111@gmail.com>
License: MIT License
Project-URL: Homepage, https://github.com/billbillbilly/urbanworm
Keywords: urbanworm,urban-worm
Classifier: Development Status :: 2 - Pre-Alpha
Classifier: Intended Audience :: Developers
Classifier: License :: OSI Approved :: MIT License
Classifier: Natural Language :: English
Classifier: Programming Language :: Python :: 3
Classifier: Programming Language :: Python :: 3.10
Classifier: Programming Language :: Python :: 3.11
Classifier: Programming Language :: Python :: 3.12
Requires-Python: >=3.10
License-File: LICENSE
Requires-Dist: ollama
Requires-Dist: huggingface_hub
Requires-Dist: pandas
Requires-Dist: geopandas
Requires-Dist: numpy>=1.24
Requires-Dist: pydantic
Requires-Dist: pillow
Requires-Dist: opencv-python
Requires-Dist: pydantic
Requires-Dist: matplotlib
Requires-Dist: requests
Requires-Dist: tqdm
Requires-Dist: pydub
Dynamic: license-file
